sceptre_dot/__init__.py
sceptre_dot/__version__.py
sceptre_dot/index.py
sceptre_dot-0.2.dist-info/LICENCE.txt
sceptre_dot-0.2.dist-info/METADATA
sceptre_dot-0.2.dist-info/WHEEL
sceptre_dot-0.2.dist-info/entry_points.txt
sceptre_dot-0.2.dist-info/top_level.txt
sceptre_dot-0.2.dist-info/RECORD
