Metadata-Version: 2.1
Name: sceptre-dot
Version: 0.2
Summary: Generates a DOT file to visualise your sceptre environments
Home-page: https://github.com/jeshan/sceptre-dot
Author: Jeshan Babooa
Author-email: j@jeshan.co
License: BSD-2-Clause
Platform: UNKNOWN
Classifier: License :: OSI Approved :: BSD License
Classifier: Programming Language :: Python
Requires-Dist: sceptre
